LICENSE
MANIFEST.in
README.md
README.rst
setup.py
electiveGroupCvParser/CHANGELOG.md
electiveGroupCvParser/__init__.py
electiveGroupCvParser/command_line.py
electiveGroupCvParser/config.cfg
electiveGroupCvParser/constants.py
electiveGroupCvParser/custom_t.py
electiveGroupCvParser/meta.json
electiveGroupCvParser/requirements.txt
electiveGroupCvParser/resume_parser.py
electiveGroupCvParser/skills.csv
electiveGroupCvParser/tokenizer
electiveGroupCvParser/utils.py
electiveGroupCvParser.egg-info/PKG-INFO
electiveGroupCvParser.egg-info/SOURCES.txt
electiveGroupCvParser.egg-info/dependency_links.txt
electiveGroupCvParser.egg-info/entry_points.txt
electiveGroupCvParser.egg-info/not-zip-safe
electiveGroupCvParser.egg-info/requires.txt
electiveGroupCvParser.egg-info/top_level.txt
electiveGroupCvParser/__pycache__/__init__.cpython-39.pyc
electiveGroupCvParser/__pycache__/constants.cpython-39.pyc
electiveGroupCvParser/__pycache__/resume_parser.cpython-39.pyc
electiveGroupCvParser/__pycache__/utils.cpython-39.pyc
electiveGroupCvParser/ner/cfg
electiveGroupCvParser/ner/model
electiveGroupCvParser/ner/moves
electiveGroupCvParser/vocab/key2row
electiveGroupCvParser/vocab/lexemes.bin
electiveGroupCvParser/vocab/strings.json
electiveGroupCvParser/vocab/vectors