Metadata-Version: 2.1
Name: electiveGroupCvParser
Version: 1.0.1
Summary: A simple resume parser used for extracting information from resumes
Home-page: https://github.com/electivetechnology/cv-parser-python
Author: Chris Dixon
Author-email: chris@recii.io
License: GPL-3.0
Platform: UNKNOWN
Classifier: Intended Audience :: Developers
Classifier: Topic :: Software Development :: Libraries
Classifier: License :: OSI Approved :: GNU General Public License v3 (GPLv3)
Classifier: Programming Language :: Python :: 3
Classifier: Programming Language :: Python :: 3.3
Classifier: Programming Language :: Python :: 3.4
Classifier: Programming Language :: Python :: 3.5
Classifier: Programming Language :: Python :: 3.6
Classifier: Programming Language :: Python :: 3.7
License-File: LICENSE
